LICENSE
MANIFEST.in
README.md
requirements.txt
setup.cfg
setup.py
leafcart/__init__.py
leafcart/common.py
leafcart/leafcart.py
leafcart.egg-info/PKG-INFO
leafcart.egg-info/SOURCES.txt
leafcart.egg-info/dependency_links.txt
leafcart.egg-info/not-zip-safe
leafcart.egg-info/top_level.txt
tests/test_leafcart.py