Metadata-Version: 2.1
Name: leafcart
Version: 0.0.1
Summary: A python package for interactive mapping.
Home-page: https://github.com/Abubakr-Abdelrahman/leafcart
Author: Abubakr Abdelrahman
Author-email: bakriabdo57@gmail.com
License: MIT license
Keywords: leafcart
Classifier: Intended Audience :: Developers
Classifier: License :: OSI Approved :: MIT License
Classifier: Natural Language :: English
Classifier: Programming Language :: Python :: 3
Classifier: Programming Language :: Python :: 3.8
Classifier: Programming Language :: Python :: 3.9
Classifier: Programming Language :: Python :: 3.10
Classifier: Programming Language :: Python :: 3.11
Requires-Python: >=3.8
License-File: LICENSE
